{"primaryContentSections":[{"declarations":[{"tokens":[{"text":"struct","kind":"keyword"},{"text":" ","kind":"text"},{"text":"ZipOVVVOV","kind":"identifier"},{"text":"<","kind":"text"},{"text":"P0","kind":"genericParameter"},{"text":", ","kind":"text"},{"text":"P1","kind":"genericParameter"},{"text":", ","kind":"text"},{"text":"P2","kind":"genericParameter"},{"text":", ","kind":"text"},{"text":"P3","kind":"genericParameter"},{"text":", ","kind":"text"},{"text":"P4","kind":"genericParameter"},{"text":", ","kind":"text"},{"text":"P5","kind":"genericParameter"},{"text":"> ","kind":"text"},{"text":"where","kind":"keyword"},{"text":" ","kind":"text"},{"text":"P0","kind":"typeIdentifier"},{"text":" : ","kind":"text"},{"text":"Parser","identifier":"doc:\/\/co.pointfree.Parsing\/documentation\/Parsing\/Parser","preciseIdentifier":"s:7Parsing6ParserP","kind":"typeIdentifier"},{"text":", ","kind":"text"},{"text":"P1","kind":"typeIdentifier"},{"text":" : ","kind":"text"},{"text":"Parser","identifier":"doc:\/\/co.pointfree.Parsing\/documentation\/Parsing\/Parser","preciseIdentifier":"s:7Parsing6ParserP","kind":"typeIdentifier"},{"text":", ","kind":"text"},{"text":"P2","kind":"typeIdentifier"},{"text":" : ","kind":"text"},{"text":"Parser","identifier":"doc:\/\/co.pointfree.Parsing\/documentation\/Parsing\/Parser","preciseIdentifier":"s:7Parsing6ParserP","kind":"typeIdentifier"},{"text":", ","kind":"text"},{"text":"P3","kind":"typeIdentifier"},{"text":" : ","kind":"text"},{"text":"Parser","identifier":"doc:\/\/co.pointfree.Parsing\/documentation\/Parsing\/Parser","preciseIdentifier":"s:7Parsing6ParserP","kind":"typeIdentifier"},{"text":", ","kind":"text"},{"text":"P4","kind":"typeIdentifier"},{"text":" : ","kind":"text"},{"text":"Parser","identifier":"doc:\/\/co.pointfree.Parsing\/documentation\/Parsing\/Parser","preciseIdentifier":"s:7Parsing6ParserP","kind":"typeIdentifier"},{"text":", ","kind":"text"},{"text":"P5","kind":"typeIdentifier"},{"text":" : ","kind":"text"},{"text":"Parser","identifier":"doc:\/\/co.pointfree.Parsing\/documentation\/Parsing\/Parser","preciseIdentifier":"s:7Parsing6ParserP","kind":"typeIdentifier"},{"text":", ","kind":"text"},{"text":"P0","kind":"typeIdentifier"},{"text":".","kind":"text"},{"text":"Input","kind":"typeIdentifier"},{"text":" == ","kind":"text"},{"text":"P1","kind":"typeIdentifier"},{"text":".","kind":"text"},{"text":"Input","kind":"typeIdentifier"},{"text":", ","kind":"text"},{"text":"P1","kind":"typeIdentifier"},{"text":".","kind":"text"},{"text":"Input","kind":"typeIdentifier"},{"text":" == ","kind":"text"},{"text":"P2","kind":"typeIdentifier"},{"text":".","kind":"text"},{"text":"Input","kind":"typeIdentifier"},{"text":", ","kind":"text"},{"text":"P1","kind":"typeIdentifier"},{"text":".","kind":"text"},{"text":"Output","kind":"typeIdentifier"},{"text":" == ","kind":"text"},{"text":"Void","preciseIdentifier":"s:s4Voida","kind":"typeIdentifier"},{"text":", ","kind":"text"},{"text":"P2","kind":"typeIdentifier"},{"text":".","kind":"text"},{"text":"Input","kind":"typeIdentifier"},{"text":" == ","kind":"text"},{"text":"P3","kind":"typeIdentifier"},{"text":".","kind":"text"},{"text":"Input","kind":"typeIdentifier"},{"text":", ","kind":"text"},{"text":"P2","kind":"typeIdentifier"},{"text":".","kind":"text"},{"text":"Output","kind":"typeIdentifier"},{"text":" == ","kind":"text"},{"text":"Void","preciseIdentifier":"s:s4Voida","kind":"typeIdentifier"},{"text":", ","kind":"text"},{"text":"P3","kind":"typeIdentifier"},{"text":".","kind":"text"},{"text":"Input","kind":"typeIdentifier"},{"text":" == ","kind":"text"},{"text":"P4","kind":"typeIdentifier"},{"text":".","kind":"text"},{"text":"Input","kind":"typeIdentifier"},{"text":", ","kind":"text"},{"text":"P3","kind":"typeIdentifier"},{"text":".","kind":"text"},{"text":"Output","kind":"typeIdentifier"},{"text":" == ","kind":"text"},{"text":"Void","preciseIdentifier":"s:s4Voida","kind":"typeIdentifier"},{"text":", ","kind":"text"},{"text":"P4","kind":"typeIdentifier"},{"text":".","kind":"text"},{"text":"Input","kind":"typeIdentifier"},{"text":" == ","kind":"text"},{"text":"P5","kind":"typeIdentifier"},{"text":".","kind":"text"},{"text":"Input","kind":"typeIdentifier"},{"text":", ","kind":"text"},{"text":"P5","kind":"typeIdentifier"},{"text":".","kind":"text"},{"text":"Output","kind":"typeIdentifier"},{"text":" == ","kind":"text"},{"text":"Void","preciseIdentifier":"s:s4Voida","kind":"typeIdentifier"}],"languages":["swift"],"platforms":["Linux"]}],"kind":"declarations"}],"abstract":[{"type":"text","text":"No overview available."}],"schemaVersion":{"minor":2,"patch":0,"major":0},"variants":[{"traits":[{"interfaceLanguage":"swift"}],"paths":["\/documentation\/parsing\/parsers\/zipovvvov"]}],"hierarchy":{"paths":[["doc:\/\/co.pointfree.Parsing\/documentation\/Parsing","doc:\/\/co.pointfree.Parsing\/documentation\/Parsing\/Parsers"]]},"relationshipsSections":[{"type":"conformsTo","identifiers":["doc:\/\/co.pointfree.Parsing\/documentation\/Parsing\/Parser"],"kind":"relationships","title":"Conforms To"}],"topicSections":[{"identifiers":["doc:\/\/co.pointfree.Parsing\/documentation\/Parsing\/Parsers\/ZipOVVVOV\/init(_:_:_:_:_:_:)"],"title":"Initializers"},{"identifiers":["doc:\/\/co.pointfree.Parsing\/documentation\/Parsing\/Parsers\/ZipOVVVOV\/p0","doc:\/\/co.pointfree.Parsing\/documentation\/Parsing\/Parsers\/ZipOVVVOV\/p1","doc:\/\/co.pointfree.Parsing\/documentation\/Parsing\/Parsers\/ZipOVVVOV\/p2","doc:\/\/co.pointfree.Parsing\/documentation\/Parsing\/Parsers\/ZipOVVVOV\/p3","doc:\/\/co.pointfree.Parsing\/documentation\/Parsing\/Parsers\/ZipOVVVOV\/p4","doc:\/\/co.pointfree.Parsing\/documentation\/Parsing\/Parsers\/ZipOVVVOV\/p5"],"title":"Instance Properties"},{"identifiers":["doc:\/\/co.pointfree.Parsing\/documentation\/Parsing\/Parsers\/ZipOVVVOV\/parse(_:)"],"title":"Instance Methods"},{"identifiers":["doc:\/\/co.pointfree.Parsing\/documentation\/Parsing\/Parsers\/ZipOVVVOV\/Parser-Implementations"],"generated":true,"title":"Default Implementations"}],"kind":"symbol","sections":[],"identifier":{"interfaceLanguage":"swift","url":"doc:\/\/co.pointfree.Parsing\/documentation\/Parsing\/Parsers\/ZipOVVVOV"},"metadata":{"title":"Parsers.ZipOVVVOV","extendedModule":"Parsing","navigatorTitle":[{"text":"ZipOVVVOV","kind":"identifier"}],"role":"symbol","symbolKind":"struct","externalID":"s:7Parsing7ParsersO9ZipOVVVOVV","fragments":[{"text":"struct","kind":"keyword"},{"text":" ","kind":"text"},{"text":"ZipOVVVOV","kind":"identifier"}],"modules":[{"name":"Parsing"}],"roleHeading":"Structure"},"references":{"doc://co.pointfree.Parsing/documentation/Parsing/Parsers/ZipOVVVOV/p1":{"abstract":[],"identifier":"doc:\/\/co.pointfree.Parsing\/documentation\/Parsing\/Parsers\/ZipOVVVOV\/p1","title":"p1","fragments":[{"text":"let","kind":"keyword"},{"text":" ","kind":"text"},{"text":"p1","kind":"identifier"},{"text":": ","kind":"text"},{"text":"P1","kind":"typeIdentifier"}],"kind":"symbol","role":"symbol","url":"\/documentation\/parsing\/parsers\/zipovvvov\/p1","type":"topic"},"doc://co.pointfree.Parsing/documentation/Parsing/Parsers":{"url":"\/documentation\/parsing\/parsers","identifier":"doc:\/\/co.pointfree.Parsing\/documentation\/Parsing\/Parsers","fragments":[{"text":"enum","kind":"keyword"},{"text":" ","kind":"text"},{"text":"Parsers","kind":"identifier"}],"type":"topic","abstract":[{"text":"A namespace for types that serve as parsers.","type":"text"}],"kind":"symbol","title":"Parsers","navigatorTitle":[{"text":"Parsers","kind":"identifier"}],"role":"symbol"},"doc://co.pointfree.Parsing/documentation/Parsing/Parsers/ZipOVVVOV/Parser-Implementations":{"identifier":"doc:\/\/co.pointfree.Parsing\/documentation\/Parsing\/Parsers\/ZipOVVVOV\/Parser-Implementations","title":"Parser Implementations","type":"topic","abstract":[],"kind":"article","url":"\/documentation\/parsing\/parsers\/zipovvvov\/parser-implementations","role":"collectionGroup"},"doc://co.pointfree.Parsing/documentation/Parsing/Parsers/ZipOVVVOV/p0":{"type":"topic","identifier":"doc:\/\/co.pointfree.Parsing\/documentation\/Parsing\/Parsers\/ZipOVVVOV\/p0","url":"\/documentation\/parsing\/parsers\/zipovvvov\/p0","role":"symbol","fragments":[{"kind":"keyword","text":"let"},{"kind":"text","text":" "},{"kind":"identifier","text":"p0"},{"kind":"text","text":": "},{"kind":"typeIdentifier","text":"P0"}],"abstract":[],"title":"p0","kind":"symbol"},"doc://co.pointfree.Parsing/documentation/Parsing/Parsers/ZipOVVVOV/p5":{"fragments":[{"text":"let","kind":"keyword"},{"text":" ","kind":"text"},{"text":"p5","kind":"identifier"},{"text":": ","kind":"text"},{"text":"P5","kind":"typeIdentifier"}],"role":"symbol","title":"p5","abstract":[],"kind":"symbol","url":"\/documentation\/parsing\/parsers\/zipovvvov\/p5","type":"topic","identifier":"doc:\/\/co.pointfree.Parsing\/documentation\/Parsing\/Parsers\/ZipOVVVOV\/p5"},"doc://co.pointfree.Parsing/documentation/Parsing/Parsers/ZipOVVVOV":{"navigatorTitle":[{"text":"ZipOVVVOV","kind":"identifier"}],"fragments":[{"text":"struct","kind":"keyword"},{"text":" ","kind":"text"},{"text":"ZipOVVVOV","kind":"identifier"}],"identifier":"doc:\/\/co.pointfree.Parsing\/documentation\/Parsing\/Parsers\/ZipOVVVOV","title":"Parsers.ZipOVVVOV","type":"topic","abstract":[],"kind":"symbol","url":"\/documentation\/parsing\/parsers\/zipovvvov","role":"symbol"},"doc://co.pointfree.Parsing/documentation/Parsing/Parsers/ZipOVVVOV/p3":{"title":"p3","fragments":[{"text":"let","kind":"keyword"},{"text":" ","kind":"text"},{"text":"p3","kind":"identifier"},{"text":": ","kind":"text"},{"text":"P3","kind":"typeIdentifier"}],"role":"symbol","url":"\/documentation\/parsing\/parsers\/zipovvvov\/p3","abstract":[],"kind":"symbol","identifier":"doc:\/\/co.pointfree.Parsing\/documentation\/Parsing\/Parsers\/ZipOVVVOV\/p3","type":"topic"},"doc://co.pointfree.Parsing/documentation/Parsing/Parsers/ZipOVVVOV/p4":{"role":"symbol","type":"topic","identifier":"doc:\/\/co.pointfree.Parsing\/documentation\/Parsing\/Parsers\/ZipOVVVOV\/p4","url":"\/documentation\/parsing\/parsers\/zipovvvov\/p4","kind":"symbol","title":"p4","abstract":[],"fragments":[{"kind":"keyword","text":"let"},{"kind":"text","text":" "},{"kind":"identifier","text":"p4"},{"kind":"text","text":": "},{"kind":"typeIdentifier","text":"P4"}]},"doc://co.pointfree.Parsing/documentation/Parsing/Parsers/ZipOVVVOV/p2":{"title":"p2","fragments":[{"text":"let","kind":"keyword"},{"text":" ","kind":"text"},{"text":"p2","kind":"identifier"},{"text":": ","kind":"text"},{"text":"P2","kind":"typeIdentifier"}],"identifier":"doc:\/\/co.pointfree.Parsing\/documentation\/Parsing\/Parsers\/ZipOVVVOV\/p2","type":"topic","kind":"symbol","url":"\/documentation\/parsing\/parsers\/zipovvvov\/p2","abstract":[],"role":"symbol"},"doc://co.pointfree.Parsing/documentation/Parsing":{"url":"\/documentation\/parsing","identifier":"doc:\/\/co.pointfree.Parsing\/documentation\/Parsing","type":"topic","abstract":[],"kind":"symbol","title":"Parsing","role":"collection"},"doc://co.pointfree.Parsing/documentation/Parsing/Parsers/ZipOVVVOV/init(_:_:_:_:_:_:)":{"title":"init(_:_:_:_:_:_:)","role":"symbol","abstract":[],"type":"topic","url":"\/documentation\/parsing\/parsers\/zipovvvov\/init(_:_:_:_:_:_:)","kind":"symbol","identifier":"doc:\/\/co.pointfree.Parsing\/documentation\/Parsing\/Parsers\/ZipOVVVOV\/init(_:_:_:_:_:_:)","fragments":[{"kind":"identifier","text":"init"},{"kind":"text","text":"("},{"kind":"typeIdentifier","text":"P0"},{"kind":"text","text":", "},{"kind":"typeIdentifier","text":"P1"},{"kind":"text","text":", "},{"kind":"typeIdentifier","text":"P2"},{"kind":"text","text":", "},{"kind":"typeIdentifier","text":"P3"},{"kind":"text","text":", "},{"kind":"typeIdentifier","text":"P4"},{"kind":"text","text":", "},{"kind":"typeIdentifier","text":"P5"},{"kind":"text","text":")"}]},"doc://co.pointfree.Parsing/documentation/Parsing/Parsers/ZipOVVVOV/parse(_:)":{"title":"parse(_:)","role":"symbol","abstract":[{"type":"text","text":"Attempts to parse a nebulous piece of data into something more well-structured."}],"type":"topic","url":"\/documentation\/parsing\/parsers\/zipovvvov\/parse(_:)","kind":"symbol","identifier":"doc:\/\/co.pointfree.Parsing\/documentation\/Parsing\/Parsers\/ZipOVVVOV\/parse(_:)","fragments":[{"kind":"keyword","text":"func"},{"kind":"text","text":" "},{"kind":"identifier","text":"parse"},{"kind":"text","text":"("},{"kind":"keyword","text":"inout"},{"kind":"text","text":" "},{"kind":"typeIdentifier","text":"P0"},{"kind":"text","text":"."},{"kind":"typeIdentifier","text":"Input"},{"kind":"text","text":") "},{"kind":"keyword","text":"rethrows"},{"kind":"text","text":" -> ("},{"kind":"typeIdentifier","text":"P0"},{"kind":"text","text":"."},{"kind":"typeIdentifier","text":"Output"},{"kind":"text","text":", "},{"kind":"typeIdentifier","text":"P4"},{"kind":"text","text":"."},{"kind":"typeIdentifier","text":"Output"},{"kind":"text","text":")"}]},"doc://co.pointfree.Parsing/documentation/Parsing/Parser":{"abstract":[{"type":"text","text":"Declares a type that can parse an "},{"code":"Input","type":"codeVoice"},{"type":"text","text":" value into an "},{"code":"Output","type":"codeVoice"},{"type":"text","text":" value."}],"url":"\/documentation\/parsing\/parser","title":"Parser","type":"topic","identifier":"doc:\/\/co.pointfree.Parsing\/documentation\/Parsing\/Parser","fragments":[{"kind":"keyword","text":"protocol"},{"kind":"text","text":" "},{"kind":"identifier","text":"Parser"}],"role":"symbol","navigatorTitle":[{"kind":"identifier","text":"Parser"}],"kind":"symbol"}}}